webpack_pages/__init__.py
webpack_pages/jinja2ext.py
webpack_pages/pageassetfinder.py
webpack_pages/templatetags.py
webpack_pages/utils.py
django_webpack_pages-0.2.0.dist-info/METADATA
django_webpack_pages-0.2.0.dist-info/WHEEL
django_webpack_pages-0.2.0.dist-info/RECORD
