Metadata-Version: 2.4
Name: django-webpack-pages
Version: 0.2.0
Summary: Use webpack with your multi-page, multi-lingual django webapp
License: MIT
Keywords: django,webpack,assets
Author: MrP01
Author-email: peter@waldert.at
Requires-Python: >=3.12,<4.0
Classifier: License :: OSI Approved :: MIT License
Classifier: Programming Language :: Python :: 3
Classifier: Programming Language :: Python :: 3.12
Classifier: Programming Language :: Python :: 3.13
Classifier: Programming Language :: Python :: 3.14
Requires-Dist: Django (>=5.2)
Requires-Dist: Jinja2 (>=3.1.6,<4.0.0)
Requires-Dist: django-webpack-loader (>=3.1.1,<4.0.0)
Project-URL: Homepage, https://github.com/MrP01/django-webpack-pages
